auto_ml_kinder/__init__.py
auto_ml_kinder/model_feature_selector.py
auto_ml_kinder/model_list_helper.py
auto_ml_kinder/model_training_data_prep.py
auto_ml_kinder/model_training_helper.py
auto_ml_kinder/pre_processing.py
auto_ml_kinder/classes/Functions.py
auto_ml_kinder/classes/ModelAndParamClassifiction.py
auto_ml_kinder/classes/ModelAndParamRegression.py
auto_ml_kinder/classes/ModelMeta.py
auto_ml_kinder/classes/ModelPerformance.py
auto_ml_kinder/classes/ModelPower.py
auto_ml_kinder/classes/ModelTrainer.py
auto_ml_kinder/classes/ModelTrainingData.py
auto_ml_kinder/classes/NeuralNetwork_BayesianOptimization.py
auto_ml_kinder/classes/NeuralNetwork_BayesianOptimization_Params.py
auto_ml_kinder/classes/NeuralNetwork_Classification.py
auto_ml_kinder/classes/NeuralNetwork_Params.py
auto_ml_kinder/classes/NeuralNetwork_Regression.py
auto_ml_kinder/classes/ScalerType.py
auto_ml_kinder/classes/__init__.py
auto_ml_kinder-0.0.26.dist-info/LICENSE
auto_ml_kinder-0.0.26.dist-info/METADATA
auto_ml_kinder-0.0.26.dist-info/WHEEL
auto_ml_kinder-0.0.26.dist-info/top_level.txt
auto_ml_kinder-0.0.26.dist-info/RECORD
