Metadata-Version: 2.2
Name: auto_ml_kinder
Version: 0.0.26
Summary: A small automated ML package
Author-email: Kinderpreet Singh <author@example.com>
Classifier: Programming Language :: Python :: 3
Requires-Python: >=3.8
License-File: LICENSE
Requires-Dist: numpy>=1.18.0
Requires-Dist: pandas>=1.0.0
Requires-Dist: scikeras
